Workbook

Sheet Inputs
A1: LeaseRight — pilot pricing and payment-volume sensitivity
A2: Calculated outputs on 'PPV Sensitivity', 'Scale to $1M', and the reconciliation block on 'Sources' are formulas driven by column B of this sheet. 'Pilot Fee' also carries direct inputs of its own: the deliverable hours in C7:C19.
A3: This workbook sets no pilot price and recommends none. B34 is an empty decision cell for Justin.
A4: Source document: spec/OVERSEER_MODEL_AND_AGENT_SYNTHESIS.md (as of 2026-09-02). STATED = the synthesis states it. INFERRED = derived by the workbook author and not in the synthesis. NOT STATED = the synthesis leaves it open. See the 'Sources' sheet for the citation behind every seeded cell.
A6: Input | B6: Value | C6: Unit | D6: Status | E6: Synthesis section
A7: — Payment-volume base —
A8: Total units | B8: 260 | C8: units | D8: STATED | E8: Definitions that control (L73–L75)
A9: Average monthly rent | B9: 2180 | C9: $/unit/month | D9: STATED | E9: Definitions that control (L73–L75)
A10: Occupied / collectible rent share | B10: 0.95 | C10: share of billed rent | D10: STATED | E10: Definitions that control (L75–L76)
A11: Payment adoption | B11: 0.8 | C11: share of collectible rent | D11: STATED | E11: Definitions that control (L75–L76)
A12: ACH share of routed volume | C12: share | D12: NOT STATED — Phase A evidence to obtain | E12: Phase A (L328–L330) lists method mix among the evidence to collect; it states no split
A13: Card share of routed volume | B13: =IF(B12="","",1-B12) | C13: share | D13: derived from B12 | E13: Adoption design (L157–L158) names ACH and optional card; the complement is arithmetic
A14: Note on method mix | D14: STATED | E14: Definitions that control (L69–L72): the net take rate is already defined net of all LeaseRight-borne payment costs, divided by PPV, so method mix does not change the revenue math in this workbook
A16: — Derived payment volume —
A17: Annual billed rent | B17: =B8*B9*12 | C17: $/year | D17: computed | E17: Definitions that control (L78)
A18: Base annual PPV | B18: =B17*B10*B11 | C18: $/year | D18: computed | E18: Definitions that control (L80)
A19: PPV per total unit per year | B19: =IF(B8=0,"",B18/B8) | C19: $/unit/year | D19: computed | E19: Definitions that control (L81)
A21: — Net LeaseRight take-rate cases —
A22: Case 1 — residual downside | B22: 5 | C22: bps of PPV | D22: STATED | E22: The answer (L18–L20); What is realistic (L118–L120)
A23: Case 2 — underwriting screen | B23: 10 | C23: bps of PPV | D23: STATED | E23: The answer (L18–L20); What is realistic (L118–L120)
A24: Case 3 — stretch contract case | B24: 25 | C24: bps of PPV | D24: STATED — requires a written contract | E24: The answer (L20–L21); What is realistic (L118–L119)
A25: Case 4 — 50 bps | B25: NOT MODELLED | C25: — | D25: STATED EXCLUSION | E25: The answer (L21–L23): 'Do not use 50 bps in the plan: no source or proposal supports it.' No 50-bps column exists anywhere in this workbook.
A26: What-if net take (editable) | B26: 10 | C26: bps of PPV | D26: INPUT — scenario cell, set it freely | E26: No synthesis figure. Seeded at the stated 10-bps screen so the what-if column opens on the screen case (INFERRED seed).
A28: — Scale target —
A29: Annual net payment revenue target | B29: 1000000 | C29: $/year | D29: STATED | E29: The answer (L30–L31)
A30: Secondary target multiple | B30: 5 | C30: × | D30: STATED | E30: Definitions that control (L90)
A31: Units per comparable asset | B31: =B8 | C31: units | D31: STATED | E31: Definitions that control (L84–L88), '260-unit assets for $1M' column
A33: — Pilot engagement (Justin's decision inputs) —
A34: Pilot fee (fixed, upfront) | C34: $ | D34: DECISION — deliberately empty; this workbook sets no price and recommends none | E34: Commercial gate (L301–L319); Only decisions Justin must make now (L533–L541)
A35: Five-figure band — low | B35: 10000 | C35: $ | D35: INFERRED — the synthesis says 'five-figure' in words and states no numbers | E35: The answer (L44); Commercial gate (L301); Only decisions (L533)
A36: Five-figure band — high | B36: 99999 | C36: $ | D36: INFERRED — the synthesis says 'five-figure' in words and states no numbers | E36: The answer (L44); Commercial gate (L301); Only decisions (L533)
A37: Project-fee reference used in the synthesis | B37: 25000 | C37: $ | D37: STATED — a crossover reference in the retention table, not a recommended price | E37: Retention and acquisition economics (L132–L141)
A38: Blended delivery rate | C38: $/hour | D38: NOT STATED — Justin's estimate | E38: The synthesis states no rate; left empty rather than guessed
A39: Phase A duration | C39: months | D39: NOT STATED — Justin's estimate | E39: Phase A (L321–L347) is scoped by deliverables; no duration is stated
A40: Phase B duration | B40: 2 | C40: months | D40: INFERRED from a stated duration | E40: Phase B — conditional 60-day operating test (L349). 60 days entered as 2 months is the workbook author's conversion.
A41: Total delivery months | B41: =IF(B39="","",B39+B40) | C41: months | D41: computed | E41: —
A42: Project band — low unit count | B42: 100 | C42: units | D42: STATED | E42: Commercial gate (L303)
A43: Project band — high unit count | B43: 400 | C43: units | D43: STATED | E43: Commercial gate (L303)

Sheet PPV Sensitivity
A1: PPV sensitivity — annual net payment revenue across unit count and net take rate
A2: Annual net payment revenue = annual PPV × net bps ÷ 10,000. Every figure below is a formula off the 'Inputs' sheet; change Inputs!B8 (units), B9 (rent), B10, B11, or any bps cell and this grid moves.
A3: 50 bps is not modelled. Synthesis, The answer (L21–L23): 'Do not use 50 bps in the plan: no source or proposal supports it, and it would exceed the per-unit revenue of AppFolio's entire bundled value-added-services line on these rent assumptions.'
A4: Net take (bps of PPV) → | D4: =Inputs!$B$22 | E4: =Inputs!$B$23 | F4: =Inputs!$B$24 | G4: =Inputs!$B$26
A5: Total units | B5: Annual billed rent ($) | C5: Annual PPV ($) | D5: ="Net revenue @ "&Inputs!$B$22&" bps — downside ($)" | E5: ="Net revenue @ "&Inputs!$B$23&" bps — screen ($)" | F5: ="Net revenue @ "&Inputs!$B$24&" bps — stretch ($)" | G5: ="Net revenue @ what-if "&Inputs!$B$26&" bps ($)" | H5: ="Net revenue / total unit / month @ "&Inputs!$B$23&" bps ($)" | I5: Row basis
A6: =Inputs!$B$42 | B6: =IF($A6="","",$A6*Inputs!$B$9*12) | C6: =IF($B6="","",$B6*Inputs!$B$10*Inputs!$B$11) | D6: =IF($C6="","",$C6*Inputs!$B$22/10000) | E6: =IF($C6="","",$C6*Inputs!$B$23/10000) | F6: =IF($C6="","",$C6*Inputs!$B$24/10000) | G6: =IF($C6="","",$C6*Inputs!$B$26/10000) | H6: =IF(OR($A6="",$A6=0),"",$E6/$A6/12) | I6: Project band — low (STATED, Commercial gate L303)
A7: =Inputs!$B$8 | B7: =IF($A7="","",$A7*Inputs!$B$9*12) | C7: =IF($B7="","",$B7*Inputs!$B$10*Inputs!$B$11) | D7: =IF($C7="","",$C7*Inputs!$B$22/10000) | E7: =IF($C7="","",$C7*Inputs!$B$23/10000) | F7: =IF($C7="","",$C7*Inputs!$B$24/10000) | G7: =IF($C7="","",$C7*Inputs!$B$26/10000) | H7: =IF(OR($A7="",$A7=0),"",$E7/$A7/12) | I7: Base stabilized asset (STATED, Definitions that control L73–L75)
A8: =Inputs!$B$43 | B8: =IF($A8="","",$A8*Inputs!$B$9*12) | C8: =IF($B8="","",$B8*Inputs!$B$10*Inputs!$B$11) | D8: =IF($C8="","",$C8*Inputs!$B$22/10000) | E8: =IF($C8="","",$C8*Inputs!$B$23/10000) | F8: =IF($C8="","",$C8*Inputs!$B$24/10000) | G8: =IF($C8="","",$C8*Inputs!$B$26/10000) | H8: =IF(OR($A8="",$A8=0),"",$E8/$A8/12) | I8: Project band — high (STATED, Commercial gate L303)
A9: =Inputs!$B$8*10 | B9: =IF($A9="","",$A9*Inputs!$B$9*12) | C9: =IF($B9="","",$B9*Inputs!$B$10*Inputs!$B$11) | D9: =IF($C9="","",$C9*Inputs!$B$22/10000) | E9: =IF($C9="","",$C9*Inputs!$B$23/10000) | F9: =IF($C9="","",$C9*Inputs!$B$24/10000) | G9: =IF($C9="","",$C9*Inputs!$B$26/10000) | H9: =IF(OR($A9="",$A9=0),"",$E9/$A9/12) | I9: 10 × base asset (grid step, INFERRED)
A10: =Inputs!$B$8*50 | B10: =IF($A10="","",$A10*Inputs!$B$9*12) | C10: =IF($B10="","",$B10*Inputs!$B$10*Inputs!$B$11) | D10: =IF($C10="","",$C10*Inputs!$B$22/10000) | E10: =IF($C10="","",$C10*Inputs!$B$23/10000) | F10: =IF($C10="","",$C10*Inputs!$B$24/10000) | G10: =IF($C10="","",$C10*Inputs!$B$26/10000) | H10: =IF(OR($A10="",$A10=0),"",$E10/$A10/12) | I10: 50 × base asset (grid step, INFERRED)
A11: =Inputs!$B$8*100 | B11: =IF($A11="","",$A11*Inputs!$B$9*12) | C11: =IF($B11="","",$B11*Inputs!$B$10*Inputs!$B$11) | D11: =IF($C11="","",$C11*Inputs!$B$22/10000) | E11: =IF($C11="","",$C11*Inputs!$B$23/10000) | F11: =IF($C11="","",$C11*Inputs!$B$24/10000) | G11: =IF($C11="","",$C11*Inputs!$B$26/10000) | H11: =IF(OR($A11="",$A11=0),"",$E11/$A11/12) | I11: 100 × base asset (grid step, INFERRED)
A12: =Inputs!$B$8*200 | B12: =IF($A12="","",$A12*Inputs!$B$9*12) | C12: =IF($B12="","",$B12*Inputs!$B$10*Inputs!$B$11) | D12: =IF($C12="","",$C12*Inputs!$B$22/10000) | E12: =IF($C12="","",$C12*Inputs!$B$23/10000) | F12: =IF($C12="","",$C12*Inputs!$B$24/10000) | G12: =IF($C12="","",$C12*Inputs!$B$26/10000) | H12: =IF(OR($A12="",$A12=0),"",$E12/$A12/12) | I12: 200 × base asset (grid step, INFERRED)
A13: =Inputs!$B$8*400 | B13: =IF($A13="","",$A13*Inputs!$B$9*12) | C13: =IF($B13="","",$B13*Inputs!$B$10*Inputs!$B$11) | D13: =IF($C13="","",$C13*Inputs!$B$22/10000) | E13: =IF($C13="","",$C13*Inputs!$B$23/10000) | F13: =IF($C13="","",$C13*Inputs!$B$24/10000) | G13: =IF($C13="","",$C13*Inputs!$B$26/10000) | H13: =IF(OR($A13="",$A13=0),"",$E13/$A13/12) | I13: 400 × base asset (grid step, INFERRED) — brackets the stated 50K–101K units
A15: Row 7 is the synthesis base case. It reproduces $6,801,600 of annual billed rent and $5,169,216 of annual PPV exactly, and $2,584.61 / $5,169.22 / $12,923.04 of annual net revenue at 5 / 10 / 25 bps and $1.6568 per total unit per month at the 10-bps screen against the synthesis's display-rounded $2,585 / $5,169 / $12,923 and $1.66 (Definitions that control, L78–L88). The 'Sources' sheet carries the live reconciliation of each of those figures, with the rounding difference shown rather than hidden.
A16: Unit-ladder rows 9–13 are INFERRED grid steps. The synthesis states no unit ladder; these multiples were chosen to bracket its stated 50K–101K unit requirement and are formulas off Inputs!B8, so they move with the base asset.

Sheet Scale to $1M
A1: Scale to $1M of annual net payment revenue
A2: Target = Inputs!B29. Secondary target = target × Inputs!B30. Comparable asset size = Inputs!B31 units. Every figure below is a formula off 'Inputs'.
A3: Synthesis, The answer (L30–L31): 'Reaching $1M of annual net payment revenue requires about $1B–$2B of PPV, or roughly 50K–101K comparable total units.'
A4: Requirement | B4: ="@ "&Inputs!$B$22&" bps — residual downside" | C4: ="@ "&Inputs!$B$23&" bps — underwriting screen" | D4: ="@ "&Inputs!$B$24&" bps — stretch contract case" | E4: ="@ what-if "&Inputs!$B$26&" bps"
A5: Net take (bps of PPV) | B5: =Inputs!$B$22 | C5: =Inputs!$B$23 | D5: =Inputs!$B$24 | E5: =Inputs!$B$26
A6: PPV required for the target ($) | B6: =IF(B$5="","",Inputs!$B$29/(B$5/10000)) | C6: =IF(C$5="","",Inputs!$B$29/(C$5/10000)) | D6: =IF(D$5="","",Inputs!$B$29/(D$5/10000)) | E6: =IF(E$5="","",Inputs!$B$29/(E$5/10000))
A7: Total units required (at Inputs!B19 PPV per total unit per year) | B7: =IF(OR(B$6="",Inputs!$B$19=""),"",B$6/Inputs!$B$19) | C7: =IF(OR(C$6="",Inputs!$B$19=""),"",C$6/Inputs!$B$19) | D7: =IF(OR(D$6="",Inputs!$B$19=""),"",D$6/Inputs!$B$19) | E7: =IF(OR(E$6="",Inputs!$B$19=""),"",E$6/Inputs!$B$19)
A8: Comparable assets required (Inputs!B31 units each) | B8: =IF(B$7="","",ROUNDUP(B$7/Inputs!$B$31,0)) | C8: =IF(C$7="","",ROUNDUP(C$7/Inputs!$B$31,0)) | D8: =IF(D$7="","",ROUNDUP(D$7/Inputs!$B$31,0)) | E8: =IF(E$7="","",ROUNDUP(E$7/Inputs!$B$31,0))
A9: PPV required for the secondary target ($) | B9: =IF(B$6="","",B$6*Inputs!$B$30) | C9: =IF(C$6="","",C$6*Inputs!$B$30) | D9: =IF(D$6="","",D$6*Inputs!$B$30) | E9: =IF(E$6="","",E$6*Inputs!$B$30)
A10: Total units required for the secondary target | B10: =IF(B$7="","",B$7*Inputs!$B$30) | C10: =IF(C$7="","",C$7*Inputs!$B$30) | D10: =IF(D$7="","",D$7*Inputs!$B$30) | E10: =IF(E$7="","",E$7*Inputs!$B$30)
A11: Comparable assets for the secondary target | B11: =IF(B$10="","",ROUNDUP(B$10/Inputs!$B$31,0)) | C11: =IF(C$10="","",ROUNDUP(C$10/Inputs!$B$31,0)) | D11: =IF(D$10="","",ROUNDUP(D$10/Inputs!$B$31,0)) | E11: =IF(E$10="","",ROUNDUP(E$10/Inputs!$B$31,0))
A13: Rows 9–11 apply the stated instruction: 'For $5M of annual net payment revenue, multiply every PPV, unit, and asset requirement by five.' (Definitions that control, L90)
A14: No 50-bps column exists here, by instruction of the synthesis (The answer, L21–L23).
A15: These requirements move when Inputs!B8, B9, B10, B11 or any bps cell changes, because Inputs!B19 (PPV per total unit per year) drives the unit and asset counts.

Sheet Pilot Fee
A1: Pilot fee — deliverable build-up for the fixed, upfront, stage-gated engagement
A2: This workbook sets no price and recommends none. The fee is an input: Inputs!B34, currently empty. The rows below scope what the fee must cover, transcribed from the synthesis. The hours in column C and the blended rate in Inputs!B38 are Justin's estimates, not figures from the synthesis.
A3: Synthesis, Commercial gate (L315–L317): 'The fixed fee covers the Model calibration, frozen launch baseline, weekly variance output, payment diligence, and the conditional operating test.' Remaining risks (L518): 'the first fixed fee must therefore be scoped from deliverables and project band.'
A5: Stage | B5: Scoped deliverable (transcribed from the synthesis) | C5: Hours (input — empty) | D5: Blended rate ($/hr, Inputs!B38) | E5: Cost ($) | F5: Synthesis section
A7: Commercial gate | B7: Signed fixed-fee scope for one real 100–400-unit lease-up in one launch market, with the upfront payment collected | D7: =IF(Inputs!$B$38="","",Inputs!$B$38) | E7: =IF(OR($C7="",Inputs!$B$38=""),"",$C7*Inputs!$B$38) | F7: Commercial gate (L303–L318)
A8: Commercial gate | B8: Counsel-drafted continuity term sheet: assignment or commercially reasonable assignment efforts on sale, payment-path continuity or a right to bid on a successor PM, right of first refusal on payment processing at stabilization, and disclosure of lender cash-management provisions | D8: =IF(Inputs!$B$38="","",Inputs!$B$38) | E8: =IF(OR($C8="",Inputs!$B$38=""),"",$C8*Inputs!$B$38) | F8: Commercial gate (L308–L314)
A9: Phase A | B9: Pilot Model rebuilt from the sponsor's source underwriting and operating records | D9: =IF(Inputs!$B$38="","",Inputs!$B$38) | E9: =IF(OR($C9="",Inputs!$B$38=""),"",$C9*Inputs!$B$38) | F9: Phase A (L323–L325)
A10: Phase A | B10: One agreed delivery schedule, stabilization definition, lease count, velocity convention, carry rate, concession method, and scenario formula, with every displayed date and cost derived from those inputs | D10: =IF(Inputs!$B$38="","",Inputs!$B$38) | E10: =IF(OR($C10="",Inputs!$B$38=""),"",$C10*Inputs!$B$38) | F10: Phase A (L324–L326)
A11: Phase A | B11: Frozen agreed baseline before live operations, plus the weekly variance output | D11: =IF(Inputs!$B$38="","",Inputs!$B$38) | E11: =IF(OR($C11="",Inputs!$B$38=""),"",$C11*Inputs!$B$38) | F11: Phase A (L326); Commercial gate (L315–L316)
A12: Phase A | B12: Payment diligence pack: 12 months of rent rolls and processor statements where available, method mix, fee payer, returns, disputes and failed payments, settlement timing, and reconciliation labour | D12: =IF(Inputs!$B$38="","",Inputs!$B$38) | E12: =IF(OR($C12="",Inputs!$B$38=""),"",$C12*Inputs!$B$38) | F12: Phase A (L328–L331)
A13: Phase A | B13: Contract and lender review: current PM/PMS/processor contracts and termination rights, lender lockbox/DACA requirements, and the expected post-stabilization owner/manager | D13: =IF(Inputs!$B$38="","",Inputs!$B$38) | E13: =IF(OR($C13="",Inputs!$B$38=""),"",$C13*Inputs!$B$38) | F13: Phase A (L331–L333)
A14: Phase A | B14: Written processor proposal translating any residual into net bps of PPV, stating fee base, payment-method scope, activation threshold, pricing control, reserves, loss liability, clawbacks, settlement, data access, and portability | D14: =IF(Inputs!$B$38="","",Inputs!$B$38) | E14: =IF(OR($C14="",Inputs!$B$38=""),"",$C14*Inputs!$B$38) | F14: Phase A (L332–L336)
A15: Phase A | B15: Interviews with five active local originators and two exclusive lease-up brokers on inventory freshness, registration protection, payee rules, payout timing, and buyer vs demand-source role | D15: =IF(Inputs!$B$38="","",Inputs!$B$38) | E15: =IF(OR($C15="",Inputs!$B$38=""),"",$C15*Inputs!$B$38) | F15: Phase A (L338–L341)
A16: Phase B | B16: Operator adoption test: four consecutive weeks routing at least 80% of eligible new leads through the LeaseRight flow, with the report generated from the same records and duplicate entry measured | D16: =IF(Inputs!$B$38="","",Inputs!$B$38) | E16: =IF(OR($C16="",Inputs!$B$38=""),"",$C16*Inputs!$B$38) | F16: Phase B (L351–L356)
A17: Phase B | B17: Mechanism/effect proxies against the operator's pre-pilot baseline: median lead-arrival to human-contact time, inquiry-to-tour conversion by source, and days-on-market for the stalled unit type | D17: =IF(Inputs!$B$38="","",Inputs!$B$38) | E17: =IF(OR($C17="",Inputs!$B$38=""),"",$C17*Inputs!$B$38) | F17: Phase B (L357–L361)
A18: Phase B | B18: Originator behaviour test: five active local originators invited, at least three unique client registrations, one downstream tour or application, and no unresolved attribution dispute | D18: =IF(Inputs!$B$38="","",Inputs!$B$38) | E18: =IF(OR($C18="",Inputs!$B$38=""),"",$C18*Inputs!$B$38) | F18: Phase B (L362–L366)
A19: Phase B | B19: Lender value test: one lender shown the reconciled baseline and weekly variance output, with the changed diligence request, reserve assumption, reporting requirement, or credit conversation recorded | D19: =IF(Inputs!$B$38="","",Inputs!$B$38) | E19: =IF(OR($C19="",Inputs!$B$38=""),"",$C19*Inputs!$B$38) | F19: Phase B (L367–L369)
A21: Commercial-gate subtotal | B21: rows 7–8 | C21: =IF(COUNTBLANK(C7:C8)>0,"inputs required",SUM(C7:C8)) | E21: =IF(OR(Inputs!$B$38="",COUNTBLANK(C7:C8)>0),"inputs required",SUM(C7:C8)*Inputs!$B$38) | F21: Commercial gate (L301–L319)
A22: Phase A subtotal | B22: rows 9–15 | C22: =IF(COUNTBLANK(C9:C15)>0,"inputs required",SUM(C9:C15)) | E22: =IF(OR(Inputs!$B$38="",COUNTBLANK(C9:C15)>0),"inputs required",SUM(C9:C15)*Inputs!$B$38) | F22: Phase A (L321–L347)
A23: Phase B subtotal | B23: rows 16–19 | C23: =IF(COUNTBLANK(C16:C19)>0,"inputs required",SUM(C16:C19)) | E23: =IF(OR(Inputs!$B$38="",COUNTBLANK(C16:C19)>0),"inputs required",SUM(C16:C19)*Inputs!$B$38) | F23: Phase B (L349–L369)
A24: Deliverable build-up total | B24: rows 7–19 | C24: =IF(COUNTBLANK(C7:C19)>0,"inputs required",SUM(C7:C19)) | E24: =IF(OR(Inputs!$B$38="",COUNTBLANK(C7:C19)>0),"inputs required",SUM(C7:C19)*Inputs!$B$38) | F24: Subtotals read 'inputs required' — not $0 — until Inputs!B38 and every hours cell are filled
A26: Pilot fee (Inputs!B34) — Justin's decision | C26: =IF(Inputs!$B$34="","not set — this workbook sets no price and recommends none",Inputs!$B$34) | F26: Only decisions Justin must make now (L533–L541)
A27: Fee less the deliverable build-up ($) | C27: =IF(OR(Inputs!$B$34="",Inputs!$B$38="",COUNTBLANK(C7:C19)>0),"inputs required",Inputs!$B$34-SUM(C7:C19)*Inputs!$B$38) | F27: —
A28: Fee against the INFERRED five-figure band (Inputs!B35–B36) | C28: =IF(Inputs!$B$34="","fee not set",IF(AND(Inputs!$B$34>=Inputs!$B$35,Inputs!$B$34<=Inputs!$B$36),"within the inferred five-figure band","outside the inferred five-figure band")) | F28: The answer (L44) — 'five-figure' in words only; the numeric band is INFERRED
A29: Fee less the $25K project-fee reference (Inputs!B37) ($) | C29: =IF(Inputs!$B$34="","fee not set",Inputs!$B$34-Inputs!$B$37) | F29: Retention and acquisition economics (L132–L141) — a crossover reference, not a price
A30: Implied blended rate at the fee ($/hr) | C30: =IF(OR(Inputs!$B$34="",COUNTBLANK(C7:C19)>0,SUM(C7:C19)=0),"inputs required",Inputs!$B$34/SUM(C7:C19)) | F30: —
A31: Fee per delivery month (Inputs!B41) ($) | C31: =IF(OR(Inputs!$B$34="",Inputs!$B$41=""),"inputs required",Inputs!$B$34/Inputs!$B$41) | F31: —
A32: Annual net payment revenue from one base asset at the screen case, for context ($) | C32: ='PPV Sensitivity'!E7 | F32: Definitions that control (L84–L88)
A34: Justin sets Inputs!B34 (fee), Inputs!B38 (blended rate), Inputs!B39 (Phase A months), and the hours in C7:C19. Until the rate and every hours cell are filled, the subtotals and the total read 'inputs required' rather than $0, so an unfinished estimate cannot be mistaken for a completed zero-cost one.
A35: The synthesis does not state a fee, a rate, or any hours. Nothing in this sheet proposes a number; it only shows what the fixed fee has to cover and how a fee you enter compares to that scope.

Sheet Sources
A1: Sources — every seeded assumption in this workbook and where it came from
A2: Source document: spec/OVERSEER_MODEL_AND_AGENT_SYNTHESIS.md, 'Overseer synthesis — LeaseRight model viability, payment engine, and agent role', as of 2026-09-02. Line numbers are that file's lines at the time this workbook was built.
A3: STATED = the synthesis states the figure or instruction. INFERRED = derived by the workbook author and not present in the synthesis. NOT STATED = the synthesis explicitly leaves it open. STATED EXCLUSION = the synthesis directs that it not be used.
A5: Workbook cell | B5: Seeded value / content | C5: Status | D5: Synthesis section (heading — lines) | E5: Supporting text
A6: Inputs!B8 | B6: 260 total units | C6: STATED | D6: Payment-engine underwriting › Definitions that control — L73–L75 | E6: 'Base planning inputs are 260 total units and $2,180 monthly rent from the repository…'
A7: Inputs!B9 | B7: $2,180 monthly rent | C7: STATED | D7: Payment-engine underwriting › Definitions that control — L73–L75 | E7: 'Base planning inputs are 260 total units and $2,180 monthly rent from the repository…'
A8: Inputs!B10 | B8: 95% occupied / collectible | C8: STATED | D8: Payment-engine underwriting › Definitions that control — L75–L76 | E8: '…plus explicit underwriting assumptions of 95% occupied/collectible rent and 80% payment adoption.'
A9: Inputs!B11 | B9: 80% payment adoption | C9: STATED | D9: Payment-engine underwriting › Definitions that control — L75–L76 | E9: '…plus explicit underwriting assumptions of 95% occupied/collectible rent and 80% payment adoption.'
A10: Inputs!B12 | B10: empty — no ACH/card split seeded | C10: NOT STATED | D10: What to test next › Phase A — L328–L330 | E10: 'obtain the payment evidence that can falsify the engine cheaply: 12 months of rent rolls and processor statements where available; method mix; fee payer…' The synthesis names method mix as evidence to collect and states no split, so none is seeded.
A11: Inputs!B13 | B11: 1 − B12 (formula) | C11: derived from B12 | D11: Payment-engine underwriting › Adoption design — L157–L158 | E11: 'free ACH to the resident, optional card at fully disclosed cost' — two methods are named; the complement is arithmetic, not a stated split.
A12: Inputs!B22 | B12: 5 bps — residual downside | C12: STATED | D12: The answer — L18–L20; Payment-engine underwriting › What is realistic — L118–L120 | E12: 'The commercial screen that should control is 5–10 basis points of net LeaseRight revenue on processed rent volume.' / 'screen at 10 bps, test 5 bps as downside'
A13: Inputs!B23 | B13: 10 bps — underwriting screen | C13: STATED | D13: The answer — L18–L20; Payment-engine underwriting › What is realistic — L118–L120 | E13: 'The commercial screen that should control is 5–10 basis points…' / 'screen at 10 bps, test 5 bps as downside'
A14: Inputs!B24 | B14: 25 bps — stretch contract case | C14: STATED | D14: The answer — L20–L21; Payment-engine underwriting › What is realistic — L118–L119 | E14: 'A 25-bps net take is a stretch contract case that likely requires a separate owner-funded application/platform fee or unusually favorable wholesale economics.' / 'require a written contract before using 25 bps'
A15: Inputs!B25 | B15: 50 bps — NOT MODELLED | C15: STATED EXCLUSION | D15: The answer — L21–L23; Debate reconciliation — L232; Completed in this mission — L477–L478 | E15: 'Do not use 50 bps in the plan: no source or proposal supports it…' / 'removed 50 bps from the plan because no source or proposal supports it.' No 50-bps column exists in this workbook.
A16: Inputs!B26 | B16: 10 bps what-if seed | C16: INFERRED | D16: No synthesis figure | E16: A scenario cell with no synthesis basis. Seeded at the stated 10-bps screen so the what-if column opens on the screen case; it is meant to be changed.
... A34: Whole workbook | B34: no recommended price | C34: By instruction | D34: Remaining risks — L518; Only decisions Justin must make now — L533–L541 | E34: 'the first fixed fee must therefore be scoped from deliverables and project band.' This workbook scopes; it does not price.
A36: Live reconciliation — figure as stated in the synthesis vs this workbook's formula chain
A37: Figure | B37: As stated in the synthesis | C37: Live from this workbook | D37: Difference (live − stated) | E37: Synthesis section (heading — lines)
A38: Annual billed rent ($/year) | B38: 6801600 | C38: =Inputs!B17 | D38: =IF(ISNUMBER(C38),C38-B38,"") | E38: Definitions that control — L78
A39: Base annual PPV ($/year) | B39: 5169216 | C39: =Inputs!B18 | D39: =IF(ISNUMBER(C39),C39-B39,"") | E39: Definitions that control — L80
A40: PPV per total unit per year ($) | B40: 19881 | C40: =Inputs!B19 | D40: =IF(ISNUMBER(C40),C40-B40,"") | E40: Definitions that control — L81 (the synthesis prints $19,881; the exact quotient is $19,881.60)
A41: Net revenue / total unit / month @ 10 bps ($) | B41: 1.66 | C41: ='PPV Sensitivity'!H7 | D41: =IF(ISNUMBER(C41),C41-B41,"") | E41: Definitions that control — L87
A42: Net revenue / 260-unit asset @ 5 bps ($) | B42: 2585 | C42: ='PPV Sensitivity'!D7 | D42: =IF(ISNUMBER(C42),C42-B42,"") | E42: Definitions that control — L86
A43: Net revenue / 260-unit asset @ 10 bps ($) | B43: 5169 | C43: ='PPV Sensitivity'!E7 | D43: =IF(ISNUMBER(C43),C43-B43,"") | E43: Definitions that control — L87
A44: Net revenue / 260-unit asset @ 25 bps ($) | B44: 12923 | C44: ='PPV Sensitivity'!F7 | D44: =IF(ISNUMBER(C44),C44-B44,"") | E44: Definitions that control — L88
A45: PPV for $1M of net revenue @ 5 bps ($) | B45: 2000000000 | C45: ='Scale to $1M'!B6 | D45: =IF(ISNUMBER(C45),C45-B45,"") | E45: Definitions that control — L86 ($2.0B)
A46: PPV for $1M of net revenue @ 10 bps ($) | B46: 1000000000 | C46: ='Scale to $1M'!C6 | D46: =IF(ISNUMBER(C46),C46-B46,"") | E46: Definitions that control — L87 ($1.0B)
A47: PPV for $1M of net revenue @ 25 bps ($) | B47: 400000000 | C47: ='Scale to $1M'!D6 | D47: =IF(ISNUMBER(C47),C47-B47,"") | E47: Definitions that control — L88 ($400M)
A48: Units for $1M of net revenue @ 5 bps | B48: 100596 | C48: ='Scale to $1M'!B7 | D48: =IF(ISNUMBER(C48),C48-B48,"") | E48: Definitions that control — L86
A49: Units for $1M of net revenue @ 10 bps | B49: 50298 | C49: ='Scale to $1M'!C7 | D49: =IF(ISNUMBER(C49),C49-B49,"") | E49: Definitions that control — L87
A50: Units for $1M of net revenue @ 25 bps | B50: 20119 | C50: ='Scale to $1M'!D7 | D50: =IF(ISNUMBER(C50),C50-B50,"") | E50: Definitions that control — L88
A51: 260-unit assets for $1M @ 5 bps | B51: 387 | C51: ='Scale to $1M'!B8 | D51: =IF(ISNUMBER(C51),C51-B51,"") | E51: Definitions that control — L86
A52: 260-unit assets for $1M @ 10 bps | B52: 194 | C52: ='Scale to $1M'!C8 | D52: =IF(ISNUMBER(C52),C52-B52,"") | E52: Definitions that control — L87
A53: 260-unit assets for $1M @ 25 bps | B53: 78 | C53: ='Scale to $1M'!D8 | D53: =IF(ISNUMBER(C53),C53-B53,"") | E53: Definitions that control — L88
A55: Non-zero differences above are the synthesis's own display rounding — it prints $19,881 for $19,881.60, $2,585 for $2,584.61, $1.66 for $1.6568 and 100,596 for 100,595.53. They are shown rather than hidden. The synthesis itself writes '$1B–$2B' and '50K–101K' as approximations ('about', 'roughly').
A56: Not modelled here: the retention and attrition stress test (Payment-engine underwriting › Retention and acquisition economics, L124–L153), including the 35%/15%, 60%/12% and 100%/15% cases and the 20.7 / 9.7 / 7.3 bps crossovers. Those figures are real and cited in the synthesis; this workbook's scope is PPV sensitivity, scale to target, and the pilot-fee build-up.
A57: The synthesis labels its own take-rate range an underwriting sensitivity, not evidence: 'the net take is therefore an underwriting range, not evidence of realizable margin' (Remaining risks, L500–L503). Nothing in this workbook is a quote, a proposal, or a realized margin.
